{
  "entityType" : "NOTIFICATION_TEMPLATE",
  "entity" : {
    "configuration" : {
      "attachReport" : false,
      "deliveryMethodsTemplates" : {
        "WEB" : {
          "method" : "WEB",
          "additionalConfig" : {
            "icon" : {
              "enabled" : true,
              "icon" : "info",
              "color" : "#757575"
            },
            "actionButtonConfig" : {
              "enabled" : true,
              "text" : "Go to Edge",
              "linkType" : "LINK",
              "link" : "/edgeManagement/instances/all/${edgeId}"
            }
          },
          "body" : "Edge '${edgeName}' is now ${eventType}",
          "enabled" : true,
          "subject" : "Edge connection status change"
        }
      },
      "reportTemplateId" : null,
      "timezone" : null,
      "userId" : null
    },
    "externalId" : null,
    "id" : {
      "entityType" : "NOTIFICATION_TEMPLATE",
      "id" : "23ce7e50-2158-11f1-8f13-7592a37a10f8"
    },
    "name" : "Edge connection notification",
    "notificationType" : "EDGE_CONNECTION"
  }
}